ansible_runner_kafka/__init__.py
ansible_runner_kafka/events.py
ansible_runner_kafka-0.1.dist-info/DESCRIPTION.rst
ansible_runner_kafka-0.1.dist-info/METADATA
ansible_runner_kafka-0.1.dist-info/RECORD
ansible_runner_kafka-0.1.dist-info/WHEEL
ansible_runner_kafka-0.1.dist-info/entry_points.txt
ansible_runner_kafka-0.1.dist-info/metadata.json
ansible_runner_kafka-0.1.dist-info/top_level.txt
