Metadata-Version: 2.0
Name: ansible-runner-kafka
Version: 0.1
Summary: UNKNOWN
Home-page: https://github.com/zauberpony/ansible-runner-kafka
Author: Elmar Athmer
License: Apache
Platform: UNKNOWN
Requires-Dist: confluent-kafka
